LICENSE
README.md
setup.cfg
setup.py
fetchabi/__init__.py
fetchabi/fetchabi.py
fetchabi.egg-info/PKG-INFO
fetchabi.egg-info/SOURCES.txt
fetchabi.egg-info/dependency_links.txt
fetchabi.egg-info/requires.txt
fetchabi.egg-info/top_level.txt