Metadata-Version: 2.1
Name: fetchabi
Version: 0.12
Summary: A quick python script used to fetch an ethereum smart contracts ABI, if it is available on etherscan.
Home-page: https://github.com/kkayam/fetchabi
Author: Koray
Author-email: korre.remix@gmail.com
License: MIT
Download-URL: https://github.com/kkayam/fetchabi/archive/refs/tags/v_01.tar.gz
Keywords: Ethereum,smart,contract,abi,fetch
Platform: UNKNOWN
Classifier: Development Status :: 3 - Alpha
Classifier: Intended Audience :: Developers
Classifier: Topic :: Software Development :: Build Tools
Classifier: License :: OSI Approved :: MIT License
Classifier: Programming Language :: Python :: 3
Classifier: Programming Language :: Python :: 3.4
Classifier: Programming Language :: Python :: 3.5
Classifier: Programming Language :: Python :: 3.6
License-File: LICENSE
